judy.py
setup.py
jasper_judy.egg-info/PKG-INFO
jasper_judy.egg-info/SOURCES.txt
jasper_judy.egg-info/dependency_links.txt
jasper_judy.egg-info/top_level.txt