Metadata-Version: 1.1
Name: jasper-judy
Version: 0.3
Summary: Simplified Voice Control on Raspberry Pi
Home-page: https://github.com/nickoala/judy
Author: Nick Lee
Author-email: lee1nick@yahoo.ca
License: MIT
Keywords: speech recognition voice control raspberry pi
Platform: UNKNOWN
Classifier: Development Status :: 4 - Beta
Classifier: Intended Audience :: Education
Classifier: Topic :: Software Development :: Libraries :: Python Modules
Classifier: Topic :: Multimedia :: Sound/Audio :: Speech
Classifier: Topic :: Education
Classifier: License :: OSI Approved :: MIT License
Classifier: Programming Language :: Python :: 2.7
